{
  "model_name": "all-MiniLM-L6-v2",
  "threshold": 0.85,
  "training_stats": {
    "train_auc": 1.0,
    "train_samples": 6300,
    "model_params": {
      "objective": "binary:logistic",
      "base_score": [
        0.21842106
      ],
      "booster": "gbtree",
      "colsample_bylevel": null,
      "colsample_bynode": null,
      "colsample_bytree": 0.8,
      "device": null,
      "early_stopping_rounds": null,
      "enable_categorical": false,
      "eval_metric": "auc",
      "feature_types": null,
      "feature_weights": null,
      "gamma": 0.1,
      "grow_policy": null,
      "importance_type": null,
      "interaction_constraints": null,
      "learning_rate": 0.05,
      "max_bin": null,
      "max_cat_threshold": null,
      "max_cat_to_onehot": null,
      "max_delta_step": null,
      "max_depth": 6,
      "max_leaves": null,
      "min_child_weight": 1,
      "missing": NaN,
      "monotone_constraints": null,
      "multi_strategy": null,
      "n_estimators": 300,
      "n_jobs": -1,
      "num_parallel_tree": null,
      "random_state": 42,
      "reg_alpha": 0.01,
      "reg_lambda": 1,
      "sampling_method": null,
      "scale_pos_weight": null,
      "subsample": 0.8,
      "tree_method": "hist",
      "validate_parameters": null,
      "verbosity": null,
      "use_label_encoder": false
    },
    "val_auc": 0.9994812925170067,
    "val_classification_report": {
      "0": {
        "precision": 0.9835680751173709,
        "recall": 0.9976190476190476,
        "f1-score": 0.9905437352245863,
        "support": 420.0
      },
      "1": {
        "precision": 0.9963503649635036,
        "recall": 0.975,
        "f1-score": 0.9855595667870036,
        "support": 280.0
      },
      "accuracy": 0.9885714285714285,
      "macro avg": {
        "precision": 0.9899592200404372,
        "recall": 0.9863095238095239,
        "f1-score": 0.988051651005795,
        "support": 700.0
      },
      "weighted avg": {
        "precision": 0.988680991055824,
        "recall": 0.9885714285714285,
        "f1-score": 0.9885500678495532,
        "support": 700.0
      }
    },
    "val_samples": 700
  },
  "xgb_params": {
    "n_estimators": 300,
    "learning_rate": 0.05,
    "max_depth": 6,
    "min_child_weight": 1,
    "subsample": 0.8,
    "colsample_bytree": 0.8,
    "gamma": 0.1,
    "reg_alpha": 0.01,
    "reg_lambda": 1,
    "use_label_encoder": false,
    "eval_metric": "auc",
    "tree_method": "hist",
    "n_jobs": -1,
    "random_state": 42
  },
  "is_trained": true
}